[
  {
    "game_name": "Я Армянин?",
    "game_image": "assets/images/categories/hay_es.png",
    "questions": [
        {
          "id": 1,
          "question": "Какова высочайшая горная вершина Армении?",
          "answers": [
            { "text": "Арарат" },
            { "text": "Арагац", "isCorrect": true },
            { "text": "Сисиан" },
            { "text": "Арцах" }
          ],
          "info": "Арагац — высочайшая вершина Армении (4090 м)."
        },
        {
          "id": 2,
          "question": "В каком году был основан город Ереван?",
          "answers": [
            { "text": "782 г. до н.э.", "isCorrect": true },
            { "text": "301 г." },
            { "text": "451 г." },
            { "text": "1918 г." }
          ],
          "info": "Ереван основан в 782 г. до н.э. с постройкой крепости Эребуни."
        },
        {
          "id": 3,
          "question": "В каком году была провозглашена независимость Армении?",
          "answers": [
            { "text": "1988" },
            { "text": "1990" },
            { "text": "1991", "isCorrect": true },
            { "text": "1992" }
          ],
          "info": "Независимость Армении провозглашена 21 сентября 1991 года."
        },
        {
          "id": 4,
          "question": "В каком году христианство было провозглашено государственной религией в Армении?",
          "answers": [
            { "text": "405 г." },
            { "text": "301 г.", "isCorrect": true },
            { "text": "451 г." },
            { "text": "782 г. до н.э." }
          ],
          "info": "Христианство стало государственной религией в Армении в 301 году."
        },
        {
          "id": 5,
          "question": "Кто создал армянский алфавит?",
          "answers": [
            { "text": "Мовсес Хоренаци" },
            { "text": "Месроп Маштоц", "isCorrect": true },
            { "text": "Вардан Мамиконян" },
            { "text": "Тигран Великий" }
          ],
          "info": "Армянский алфавит создан Месропом Маштоцем в 405 году."
        },
        {
          "id": 6,
          "question": "При каком царе Армения достигла пика своего могущества?",
          "answers": [
            { "text": "Арташес I" },
            { "text": "Тигран Великий", "isCorrect": true },
            { "text": "Арам Великий" },
            { "text": "Левон Великий" }
          ],
          "info": "При Тигране Великом Армения простиралась от Средиземного до Каспийского моря."
        },
        {
          "id": 7,
          "question": "Кто считается отцом армянской историографии?",
          "answers": [
            { "text": "Месроп Маштоц" },
            { "text": "Агатангелос" },
            { "text": "Мовсес Хоренаци", "isCorrect": true },
            { "text": "Егише" }
          ],
          "info": "Мовсес Хоренаци считается отцом армянской историографии."
        },
        {
          "id": 8,
          "question": "В каком городе была провозглашена Первая Республика Армения?",
          "answers": [
            { "text": "Ереван" },
            { "text": "Эчмиадзин" },
            { "text": "Александрополь" },
            { "text": "Тифлис", "isCorrect": true }
          ],
          "info": "Первая Республика Армения провозглашена в Тифлисе 28 мая 1918 года."
        },
        {
          "id": 9,
          "question": "В каком музее хранится клинопись об основании Эребуни?",
          "answers": [
            { "text": "Матенадаран" },
            { "text": "Музей Эребуни", "isCorrect": true },
            { "text": "Исторический музей" },
            { "text": "Музей искусств" }
          ],
          "info": "Клинопись об основании Эребуни хранится в музее Эребуни."
        },
        {
          "id": 10,
          "question": "Кто был одним из великих армянских писателей XIX века, чьи произведения оказали большое влияние на национальное самосознание?",
          "answers": [
            { "text": "Ованес Туманян" },
            { "text": "Аветик Исаакян" },
            { "text": "Раффи", "isCorrect": true },
            { "text": "Сильва Капутикян" }
          ],
          "info": "Раффи — армянский писатель XIX века, чьи исторические романы сильно повлияли на национальное самосознание."
        },
        {
          "id": 11,
          "question": "Какой католикос известен своими армянскими переводами и образовательной деятельностью?",
          "answers": [
            { "text": "Григор Лусаворич" },
            { "text": "Саак Партев", "isCorrect": true },
            { "text": "Нерсес Шнорали" },
            { "text": "Егише" }
          ],
          "info": "Саак Партев в V веке сыграл большую роль в распространении армянской письменности и переводческом движении."
        },
        {
          "id": 12,
          "question": "Какое сражение предотвратило вторжение турецких войск в Ереван в 1918 году?",
          "answers": [
            { "text": "Аварайр" },
            { "text": "Сардарапат", "isCorrect": true },
            { "text": "Баш-Апаран" },
            { "text": "Карс" }
          ],
          "info": "Сардарапатское сражение 1918 года было решающим для обеспечения существования Армении."
        },
        {
          "id": 13,
          "question": "При каком царе был построен храм Гарни?",
          "answers": [
            { "text": "Тигран Великий" },
            { "text": "Трдат I", "isCorrect": true },
            { "text": "Арташес I" },
            { "text": "Левон Великий" }
          ],
          "info": "Языческий храм Гарни построен при царе Трдате I."
        },
        {
          "id": 14,
          "question": "Какой армянский полководец участвовал в восстановлении царства Багратидов?",
          "answers": [
            { "text": "Смбат Спарапет" },
            { "text": "Вардан Мамиконян" },
            { "text": "Ашот Багратуни", "isCorrect": true },
            { "text": "Давид Бек" }
          ],
          "info": "Ашот I Багратуни в 885 году был провозглашён царём, восстановив армянское царство."
        },
        {
          "id": 15,
          "question": "Какой была столица Армянского королевства Киликия?",
          "answers": [
            { "text": "Сис", "isCorrect": true },
            { "text": "Ани" },
            { "text": "Ван" },
            { "text": "Карс" }
          ],
          "info": "Столицей Киликии был город Сис."
        },
        {
          "id": 16,
          "question": "Какой армянский полководец возглавил освободительную борьбу в Сюнике в XVIII веке?",
          "answers": [
            { "text": "Мхитар Спарапет" },
            { "text": "Давид Бек", "isCorrect": true },
            { "text": "Гарегин Нжде" },
            { "text": "Момик" }
          ],
          "info": "Давид Бек возглавил освободительную борьбу в Сюнике в 1720-х годах."
        },
        {
          "id": 17,
          "question": "В каком городе был подписан Севрский мирный договор?",
          "answers": [
            { "text": "Париж" },
            { "text": "Севр", "isCorrect": true },
            { "text": "Лондон" },
            { "text": "Вена" }
          ],
          "info": "Севрский договор подписан в 1920 году в городе Севр."
        },
        {
          "id": 18,
          "question": "Кто был премьер-министром Первой Республики Армения?",
          "answers": [
            { "text": "Грачья Ачарян" },
            { "text": "Амо Оганджанян" },
            { "text": "Ованес Каджазнуни", "isCorrect": true },
            { "text": "Арам Манукян" }
          ],
          "info": "Первым премьер-министром Армении был Ованес Каджазнуни."
        },
        {
          "id": 19,
          "question": "Кто является великим армянским поэтом, которого называют «Поэтом всех армян»?",
          "answers": [
            { "text": "Аветик Исаакян" },
            { "text": "Ованес Туманян", "isCorrect": true },
            { "text": "Паруйр Севак" },
            { "text": "Егише Чаренц" }
          ],
          "info": "Ованес Туманян считается поэтом всех армян."
        },
        {
          "id": 20,
          "question": "Какая организация признала независимость Армении в декабре 1991 года?",
          "answers": [
            { "text": "ООН" },
            { "text": "ОБСЕ" },
            { "text": "СНГ", "isCorrect": true },
            { "text": "Евросоюз" }
          ],
          "info": "СНГ признало независимость Армении в декабре 1991 года."
        },
        {
          "id": 21,
          "question": "Как называлась совместная советско-азербайджанская операция в мае-июне 1991 года, целью которой было опустошение армянских сёл Арцаха?",
          "answers": [
            { "text": "Кольцо", "isCorrect": true },
            { "text": "Комета" },
            { "text": "Кольцо" },
            { "text": "Тарон" }
          ],
          "info": "Операция известна как «Кольцо», в ходе которой насильственно депортировали жителей армянских сёл."
        },
        {
          "id": 22,
          "question": "Какой международный формат был создан в 1992 году для мирного урегулирования Карабахского конфликта?",
          "answers": [
            { "text": "Минская группа", "isCorrect": true },
            { "text": "Совет Европы" },
            { "text": "Брюссельская платформа" },
            { "text": "Пражский формат" }
          ],
          "info": "Минская группа ОБСЕ создана в 1992 году как переговорная платформа."
        },
        {
          "id": 23,
          "question": "В столице какой страны было заключено перемирие 1994 года?",
          "answers": [
            { "text": "Москва" },
            { "text": "Бишкек", "isCorrect": true },
            { "text": "Ереван" },
            { "text": "Тбилиси" }
          ],
          "info": "Перемирие заключено в столице Кыргызстана — Бишкеке."
        },
        {
          "id": 24,
          "question": "Кто был министром обороны Армении во время победы в Первой Арцахской войне?",
          "answers": [
            { "text": "Вазген Саргсян", "isCorrect": true },
            { "text": "Серж Саргсян" },
            { "text": "Манвел Григорян" },
            { "text": "Самвел Бабаян" }
          ],
          "info": "Во время окончательной победы министром обороны Армении был Вазген Саргсян."
        },
        {
          "id": 25,
          "question": "Какой армянский военачальник наиболее известен в Мартакертской битве?",
          "answers": [
            { "text": "Вазген Саргсян" },
            { "text": "Самвел Бабаян", "isCorrect": true },
            { "text": "Манвел Григорян" },
            { "text": "Аркадий Тер-Тадевосян" }
          ],
          "info": "В Мартакертской битве армянскими силами командовал Самвел Бабаян."
        },
        {
          "id": 26,
          "question": "В каком году и где погиб Монте Мелконян?",
          "answers": [
            { "text": "1992 г., Мартакерт" },
            { "text": "1993 г., Агдам" },
            { "text": "1993 г., Мартуни", "isCorrect": true },
            { "text": "1994 г., Шуши" }
          ],
          "info": "Монте Мелконян погиб 12 июня 1993 года в Мартунинском районе."
        },
        {
          "id": 27,
          "question": "Какой военный командующий руководил операцией по освобождению Шуши?",
          "answers": [
            { "text": "Мовсес Горгисян" },
            { "text": "Монте Мелконян" },
            { "text": "Аркадий Тер-Тадевосян", "isCorrect": true },
            { "text": "Самвел Бабаян" }
          ],
          "info": "Освобождением Шуши руководил Аркадий Тер-Тадевосян (Командос)."
        },
        {
          "id": 28,
          "question": "Каково было кодовое название операции по освобождению Шуши?",
          "answers": [
            { "text": "Голубь" },
            { "text": "Свадьба в горах", "isCorrect": true },
            { "text": "Свобода" },
            { "text": "Арцах" }
          ],
          "info": "Операция по освобождению Шуши носила кодовое название «Свадьба в горах»."
        },
        {
          "id": 29,
          "question": "Какая газета стала одним из важных СМИ Карабахского движения в Армении?",
          "answers": [
            { "text": "Азг" },
            { "text": "Литературная газета" },
            { "text": "Айк", "isCorrect": true },
            { "text": "Еркир" }
          ],
          "info": "Газета «Айк» сыграла большую роль в распространении идей Арцахского движения."
        },
        {
          "id": 30,
          "question": "Кто был первым президентом НКР?",
          "answers": [
            { "text": "Бако Саакян" },
            { "text": "Аркадий Гукасян" },
            { "text": "Роберт Кочарян", "isCorrect": true },
            { "text": "Араик Арутюнян" }
          ],
          "info": "Роберт Кочарян был избран первым президентом НКР."
        },
        {
          "id": 31,
          "question": "Какой военачальник был известен своим отрядом «Арцивнер» (Орлы)?",
          "answers": [
            { "text": "Вазген Саргсян" },
            { "text": "Манвел Григорян", "isCorrect": true },
            { "text": "Самвел Бабаян" },
            { "text": "Мовсес Горгисян" }
          ],
          "info": "Манвел Григорян командовал отрядом «Арцивнер»."
        },
        {
          "id": 32,
          "question": "Какова официальная дата формирования Армии обороны Арцаха?",
          "answers": [
            { "text": "1990 г." },
            { "text": "1991 г." },
            { "text": "1992 г.", "isCorrect": true },
            { "text": "1993 г." }
          ],
          "info": "Армия обороны Арцаха официально сформирована в 1992 году."
        },
        {
          "id": 33,
          "question": "В каком азербайджанском городе были сосредоточены крупные вооружённые силы, которые позже были нейтрализованы армянской стороной?",
          "answers": [
            { "text": "Гянджа" },
            { "text": "Агдам", "isCorrect": true },
            { "text": "Мингечаур" },
            { "text": "Баку" }
          ],
          "info": "Агдам был главной базой азербайджанских сил."
        },
        {
          "id": 34,
          "question": "В каком азербайджанском городе были сосредоточены крупные вооружённые силы, которые позже были нейтрализованы армянской стороной?",
          "answers": [
            { "text": "Гянджа" },
            { "text": "Агдам", "isCorrect": true },
            { "text": "Мингечаур" },
            { "text": "Баку" }
          ],
          "info": "Агдам был главной базой азербайджанских сил."
        },
        {
          "id": 35,
          "question": "В какой древней столице похоронен царь Ашот Железный?",
          "answers": [
            { "text": "Арташат" },
            { "text": "Ани" },
            { "text": "Двин", "isCorrect": true },
            { "text": "Ереван" }
          ],
          "info": "Царь Ашот Железный похоронен в городе Двин."
        },
        {
          "id": 36,
          "question": "Какая область Армении самая большая по территории?",
          "answers": [
            { "text": "Лори" },
            { "text": "Арагацотн" },
            { "text": "Сюник", "isCorrect": true },
            { "text": "Ширак" }
          ],
          "info": "Сюникская область — самая большая по территории в Армении."
        },
        {
          "id": 37,
          "question": "Кто считается «Отцом армянского естествознания»?",
          "answers": [
            { "text": "Хачатур Абовян" },
            { "text": "Виктор Амбарцумян" },
            { "text": "Анания Ширакаци", "isCorrect": true },
            { "text": "Ованес Айвазовский" }
          ],
          "info": "Анания Ширакаци считается одним из основателей армянского естествознания и астрономии."
        },
        {
          "id": 38,
          "question": "Какой национальный эпос армянского народа?",
          "answers": [
            { "text": "Сасунци Давид", "isCorrect": true },
            { "text": "Вардананк" },
            { "text": "Араратская эпоха" },
            { "text": "Эребуни" }
          ],
          "info": "Национальный эпос армян — «Сасунци Давид»."
        },
        {
          "id": 39,
          "question": "Какой самый высокий горный хребет в Армении?",
          "answers": [
            { "text": "Гегамский" },
            { "text": "Зангезурский", "isCorrect": true },
            { "text": "Арагацотнский" },
            { "text": "Варденисский" }
          ],
          "info": "Зангезурский хребет — самый высокий в Армении."
        },
        {
          "id": 40,
          "question": "Какой армянский художник является всемирно известным маринистом?",
          "answers": [
            { "text": "Мартирос Сарьян" },
            { "text": "Ованес Айвазовский", "isCorrect": true },
            { "text": "Аршил Горки" },
            { "text": "Панос Терлемезян" }
          ],
          "info": "Ованес Айвазовский — всемирно известный маринист."
        },
        {
          "id": 41,
          "question": "Какое самое высокогорное озеро Армении?",
          "answers": [
            { "text": "Арпи" },
            { "text": "Севан" },
            { "text": "Каменное озеро", "isCorrect": true },
            { "text": "Акна" }
          ],
          "info": "Каменное озеро — самое высокогорное озеро Армении, находится в Гегамских горах."
        },
        {
          "id": 42,
          "question": "Какая первая печатная армянская книга?",
          "answers": [
            { "text": "Библия" },
            { "text": "Пятничная книга (Урбатагирк)", "isCorrect": true },
            { "text": "Псалтырь" },
            { "text": "Новый Завет" }
          ],
          "info": "Первая печатная армянская книга — «Урбатагирк» (Пятничная книга), напечатана в Венеции в 1512 году."
        },
        {
          "id": 43,
          "question": "Какой армянский полководец командовал Сардарапатским сражением?",
          "answers": [
            { "text": "Андраник Озанян" },
            { "text": "Мовсес Силикян", "isCorrect": true },
            { "text": "Гарегин Нжде" },
            { "text": "Дро (Драстамат Канаян)" }
          ],
          "info": "Сардарапатским сражением командовал генерал Мовсес Силикян."
        },
        {
          "id": 44,
          "question": "В каком году была принята первая Конституция Армении?",
          "answers": [
            { "text": "1990" },
            { "text": "1995", "isCorrect": true },
            { "text": "2005" },
            { "text": "1991" }
          ],
          "info": "Первая Конституция Армении принята 5 июля 1995 года."
        },
        {
          "id": 45,
          "question": "На каком языке написано произведение «Книга скорбных песнопений» Нарекаци?",
          "answers": [
            { "text": "Ашхарабар" },
            { "text": "Грабар", "isCorrect": true },
            { "text": "Корневой армянский" },
            { "text": "Английский" }
          ],
          "info": "«Книга скорбных песнопений» Григора Нарекаци написана на грабаре (древнеармянском)."
        },
        {
          "id": 46,
          "question": "Кто был премьер-министром Первой Республики Армения?",
          "answers": [
            { "text": "Ованес Каджазнуни", "isCorrect": true },
            { "text": "Арам Манукян" },
            { "text": "Александр Хатисян" },
            { "text": "Левон Шант" }
          ],
          "info": "Первым премьер-министром Первой Республики был Ованес Каджазнуни."
        },
        {
          "id": 47,
          "question": "В каком году был основан пантеон Ераблур?",
          "answers": [
            { "text": "1990" },
            { "text": "1992" },
            { "text": "1994", "isCorrect": true },
            { "text": "1996" }
          ],
          "info": "Ераблур основан в 1994 году для увековечения памяти героев Первой Арцахской войны."
        },
        {
          "id": 48,
          "question": "Как звали лидера отрядов армянских добровольцев в годы Первой мировой войны?",
          "answers": [
            { "text": "Гарегин Нжде" },
            { "text": "Андраник Озанян", "isCorrect": true },
            { "text": "Симон Врацян" },
            { "text": "Арменак Екарян" }
          ],
          "info": "Андраник Озанян был самым известным полководцем армянского добровольческого движения."
        },
        {
          "id": 49,
          "question": "Кто записал и впервые опубликовал эпос «Сасна црер»?",
          "answers": [
            { "text": "Хачатур Абовян" },
            { "text": "Гарегин Нжде" },
            { "text": "Гарегин Срвандзтянц", "isCorrect": true },
            { "text": "Левон Шант" }
          ],
          "info": "Гарегин Срвандзтянц в XIX веке записал и опубликовал эпос «Сасна црер»."
        },
        {
          "id": 50,
          "question": "В каком году произошло Спитакское землетрясение?",
          "answers": [
            { "text": "1986" },
            { "text": "1987" },
            { "text": "1988", "isCorrect": true },
            { "text": "1989" }
          ],
          "info": "Разрушительное Спитакское землетрясение произошло 7 декабря 1988 года."
        },
        {
          "id": 51,
          "question": "Кем был герой Арцахской войны Ашот Гулян, известный как:",
          "answers": [
            { "text": "Бекор", "isCorrect": true },
            { "text": "Леон" },
            { "text": "Командос" },
            { "text": "Сисак" }
          ],
          "info": "Ашот Гулян, доброволец, был известен под именем «Бекор»."
        },
        {
          "id": 52,
          "question": "В какую эпоху был построен Эчмиадзинский кафедральный собор?",
          "answers": [
            { "text": "III век" },
            { "text": "IV век", "isCorrect": true },
            { "text": "V век" },
            { "text": "VI век" }
          ],
          "info": "Эчмиадзинский кафедральный собор построен в IV веке по инициативе Григория Просветителя."
        },
        {
          "id": 53,
          "question": "Каким был первый университет в средневековой Армении?",
          "answers": [
            { "text": "Гладзорский университет", "isCorrect": true },
            { "text": "Татевский университет" },
            { "text": "Эчмиадзинская семинария" },
            { "text": "Анийская школа" }
          ],
          "info": "Гладзорский университет основан в XIII веке и считается первым университетом Армении."
        },
        {
          "id": 54,
          "question": "Каким был первый университет в средневековой Армении?",
          "answers": [
            { "text": "Гладзорский университет", "isCorrect": true },
            { "text": "Татевский университет" },
            { "text": "Эчмиадзинская семинария" },
            { "text": "Анийская школа" }
          ],
          "info": "Гладзорский университет основан в XIII веке и считается первым университетом Армении."
        },
        {
          "id": 55,
          "question": "Какой армянский монастырь включён в список всемирного наследия ЮНЕСКО?",
          "answers": [
            { "text": "Гегард" },
            { "text": "Татев" },
            { "text": "Нораванк" },
            { "text": "Ахпат", "isCorrect": true }
          ],
          "info": "Ахпатский монастырь в Лори включён в список ЮНЕСКО."
        },
        {
          "id": 56,
          "question": "В каком году был основан Ереванский государственный университет?",
          "answers": [
            { "text": "1918" },
            { "text": "1919", "isCorrect": true },
            { "text": "1920" },
            { "text": "1921" }
          ],
          "info": "ЕГУ основан в 1919 году."
        },
        {
          "id": 57,
          "question": "Кто является одним из авторов музыки «Отче наш»?",
          "answers": [
            { "text": "Комитас", "isCorrect": true },
            { "text": "Арам Хачатурян" },
            { "text": "Тигран Мансурян" },
            { "text": "Александр Спендиарян" }
          ],
          "info": "Комитас — величайший представитель армянского духовного музыкального искусства."
        },
        {
          "id": 58,
          "question": "В каком году национальная сборная Армении по футболу провела свой первый матч?",
          "answers": [
            { "text": "1991" },
            { "text": "1992", "isCorrect": true },
            { "text": "1993" },
            { "text": "1994" }
          ],
          "info": "Национальная сборная Армении по футболу провела первый матч в 1992 году."
        },
        {
          "id": 59,
          "question": "Какова последовательность цветов государственного флага РА сверху вниз?",
          "answers": [
            { "text": "Красный-синий-оранжевый", "isCorrect": true },
            { "text": "Синий-красный-оранжевый" },
            { "text": "Оранжевый-синий-красный" },
            { "text": "Красный-оранжевый-синий" }
          ],
          "info": "Флаг РА сверху вниз: красный, синий, оранжевый."
        },
        {
          "id": 60,
          "question": "В каком городе находится мемориальный комплекс Сардарапат?",
          "answers": [
            { "text": "Гюмри" },
            { "text": "Армавир", "isCorrect": true },
            { "text": "Ванадзор" },
            { "text": "Ереван" }
          ],
          "info": "Мемориал Сардарапат находится в Армавирской области."
        },
        {
          "id": 61,
          "question": "В каком году был основан Всеармянский фонд «Айастан»?",
          "answers": [
            { "text": "1988" },
            { "text": "1989" },
            { "text": "1991" },
            { "text": "1992", "isCorrect": true }
          ],
          "info": "Всеармянский фонд «Айастан» основан в 1992 году."
        }
    ]
  }
]